{
  "courseId": "deep-learning",
  "week": 3,
  "questions": [
    {
      "id": "Q1",
      "num": 1,
      "type": "single",
      "kps": [
        "KP 4.3.2"
      ],
      "answer": "B",
      "title": "下列哪一個激發函數最有效地緩解了深層網絡中的「梯度消失」問題？",
      "options": {
        "A": "Sigmoid",
        "B": "Tanh",
        "C": "ReLU",
        "D": "Step"
      }
    },
    {
      "id": "Q2",
      "num": 2,
      "type": "single",
      "kps": [
        "KP 4.3.4"
      ],
      "answer": "C",
      "title": "在處理三分類問題的輸出層時，最適合使用的激活函數是？",
      "options": {
        "A": "Sigmoid",
        "B": "Softmax",
        "C": "ReLU",
        "D": "Linear"
      }
    },
    {
      "id": "Q3",
      "num": 3,
      "type": "single",
      "kps": [
        "KP 4.3.3"
      ],
      "answer": "A",
      "title": "交叉熵損失函數在分類問題中優於 MSE 的主要原因是？",
      "options": {
        "A": "計算速度更快",
        "B": "在預測錯誤大時能提供更強的梯度",
        "C": "它是線性的",
        "D": "它可以處理連續值"
      }
    },
    {
      "id": "Q4",
      "num": 4,
      "type": "single",
      "kps": [
        "KP 4.3.2"
      ],
      "answer": "D",
      "title": "ReLU 激發函數在輸入值小於 0 時的輸出為？",
      "options": {
        "A": "-1",
        "B": "0",
        "C": "輸入值本身",
        "D": "隨機值"
      }
    },
    {
      "id": "Q5",
      "num": 5,
      "type": "single",
      "kps": [
        "KP 4.3.5"
      ],
      "answer": "C",
      "title": "下列哪種正則化手段在訓練時隨機將部分神經元權重設為零？",
      "options": {
        "A": "L1 正則",
        "B": "L2 正則",
        "C": "Dropout",
        "D": "數據增強"
      }
    },
    {
      "id": "Q6",
      "num": 6,
      "type": "single",
      "kps": [
        "KP 4.3.1"
      ],
      "answer": "D",
      "title": "Sigmoid 函數的輸出範圍在？",
      "options": {
        "A": "[-1, 1]",
        "B": "[0, 1]",
        "C": "(0, 1)",
        "D": "$(-\\infty, \\infty)$"
      }
    },
    {
      "id": "Q7",
      "num": 7,
      "type": "single",
      "kps": [
        "KP 4.3.3"
      ],
      "answer": "B",
      "title": "損失函數 $L$ 越 __________，代表模型預測越準確。",
      "options": {
        "A": "大",
        "B": "小",
        "C": "穩定",
        "D": "接近 1"
      }
    },
    {
      "id": "Q8",
      "num": 8,
      "type": "single",
      "kps": [
        "KP 4.3.2"
      ],
      "answer": "C",
      "title": "「神經元死亡」（Dead ReLU）是指神經元輸出始終為？",
      "options": {
        "A": "1",
        "B": "0",
        "C": "負數",
        "D": "無窮大"
      }
    },
    {
      "id": "Q9",
      "num": 9,
      "type": "single",
      "kps": [
        "KP 4.3.4"
      ],
      "answer": "A",
      "title": "Softmax 函數對輸入進行指數運算的目的是？",
      "options": {
        "A": "讓大值更大，小值更小，且確保非負",
        "B": "減少計算量",
        "C": "消除偏置",
        "D": "防止過擬合"
      }
    },
    {
      "id": "Q10",
      "num": 10,
      "type": "single",
      "kps": [
        "KP 4.3.5"
      ],
      "answer": "D",
      "title": "在回歸預測任務（如房價預測）中，輸出層通常？",
      "options": {
        "A": "搭配 Sigmoid",
        "B": "搭配 Softmax",
        "C": "不使用任何激活函數 (Linear)",
        "D": "搭配 ReLU"
      }
    },
    {
      "id": "Q11",
      "num": 11,
      "type": "multiple",
      "kps": [
        "KP 4.3.1",
        "KP 4.3.2"
      ],
      "answer": [
        "A",
        "B",
        "C"
      ],
      "title": "下列屬於非線性激活函數的有？",
      "options": {
        "A": "Sigmoid",
        "B": "Tanh",
        "C": "ReLU",
        "D": "$f(x) = 2x + 1$"
      }
    },
    {
      "id": "Q12",
      "num": 12,
      "type": "multiple",
      "kps": [
        "KP 4.3.1"
      ],
      "answer": [
        "A",
        "B",
        "C",
        "D"
      ],
      "title": "Sigmoid 與 Tanh 的共同缺點包括？",
      "options": {
        "A": "都會導致梯度消失",
        "B": "運算涉及指數，相對耗時",
        "C": "輸出範圍不受限",
        "D": "容易導致神經元飽和"
      }
    },
    {
      "id": "Q13",
      "num": 13,
      "type": "multiple",
      "kps": [
        "KP 4.3.3"
      ],
      "answer": [
        "A",
        "C",
        "D"
      ],
      "title": "關於交叉熵（Cross-Entropy），描述正確的是？",
      "options": {
        "A": "它衡量兩個機率分佈的差異",
        "B": "它是二分類對數損失的推廣",
        "C": "它的值始終大於等於 0",
        "D": "它是凸函數"
      }
    },
    {
      "id": "Q14",
      "num": 14,
      "type": "multiple",
      "kps": [
        "KP 4.3.5"
      ],
      "answer": [
        "A",
        "B",
        "D"
      ],
      "title": "導致過擬合（Overfitting）的表現特徵有？",
      "options": {
        "A": "訓練誤差極低",
        "B": "測試誤差極高",
        "C": "模型記住了噪音",
        "D": "訓練誤差大於測試誤差"
      }
    },
    {
      "id": "Q15",
      "num": 15,
      "type": "multiple",
      "kps": [
        "KP 4.3.5"
      ],
      "answer": [
        "A",
        "B",
        "C",
        "D"
      ],
      "title": "Dropout 在實務中的操作包括？",
      "options": {
        "A": "只在訓練時開啟",
        "B": "在測試時應關閉並調整權重比例",
        "C": "可以隨機關閉輸入特徵",
        "D": "增加層數"
      }
    },
    {
      "id": "Q16",
      "num": 16,
      "type": "multiple",
      "kps": [
        "KP 4.3.2"
      ],
      "answer": [
        "A",
        "B",
        "D"
      ],
      "title": "ReLU 家族的變體包括？",
      "options": {
        "A": "Leaky ReLU",
        "B": "PReLU",
        "C": "ELU",
        "D": "SELU"
      }
    },
    {
      "id": "Q17",
      "num": 17,
      "type": "multiple",
      "kps": [
        "KP 4.3.3"
      ],
      "answer": [
        "A",
        "C",
        "D"
      ],
      "title": "損失函數可以分為？",
      "options": {
        "A": "分類損失",
        "B": "回歸損失",
        "C": "正則項",
        "D": "特徵矩陣"
      }
    },
    {
      "id": "Q18",
      "num": 18,
      "type": "multiple",
      "kps": [
        "KP 4.3.1"
      ],
      "answer": [
        "B",
        "C",
        "D"
      ],
      "title": "為什麼需要非線性激活函數？",
      "options": {
        "A": "否則多層網路會退化為單層線性映射",
        "B": "為了擬合非線性數據",
        "C": "為了減少參數量",
        "D": "為了引入非線性邊界"
      }
    },
    {
      "id": "Q19",
      "num": 19,
      "type": "multiple",
      "kps": [
        "KP 4.3.4"
      ],
      "answer": [
        "A",
        "C"
      ],
      "title": "Softmax 函數的特點？",
      "options": {
        "A": "輸出之和為 1",
        "B": "每個輸出都在 (0, 1) 之間",
        "C": "對極大值敏感",
        "D": "與交叉熵完美契合"
      }
    },
    {
      "id": "Q20",
      "num": 20,
      "type": "multiple",
      "kps": [
        "KP 4.3.1",
        "KP 4.3.2"
      ],
      "answer": [
        "A",
        "B",
        "C",
        "D"
      ],
      "title": "哪些手段可以預防梯度消失？",
      "options": {
        "A": "使用 ReLU",
        "B": "批量歸一化 (Batch Norm)",
        "C": "合適的權重初始化",
        "D": "增加更多 Sigmoid 層"
      }
    },
    {
      "id": "Q21",
      "num": 21,
      "type": "fill",
      "kps": [
        "KP 4.3.1"
      ],
      "answer": [
        "過擬合"
      ],
      "title": "激發函數提供了神經網路最重要的 __________ 性。"
    },
    {
      "id": "Q22",
      "num": 22,
      "type": "fill",
      "kps": [
        "KP 4.3.2"
      ],
      "answer": [
        "正則化"
      ],
      "title": "ReLU 的全稱是 __________ Linear Unit。"
    },
    {
      "id": "Q23",
      "num": 23,
      "type": "fill",
      "kps": [
        "KP 4.3.3"
      ],
      "answer": [
        "L1"
      ],
      "title": "回歸任務中，最常用的損失函數縮寫是 __________。"
    },
    {
      "id": "Q24",
      "num": 24,
      "type": "fill",
      "kps": [
        "KP 4.3.4"
      ],
      "answer": [
        "L2"
      ],
      "title": "在多分類任務中，輸出層通常使用 __________ 函數來產生機率分佈。"
    },
    {
      "id": "Q25",
      "num": 25,
      "type": "fill",
      "kps": [
        "KP 4.3.5"
      ],
      "answer": [
        "Dropout"
      ],
      "title": "__________ 是一種在訓練中隨機暫停神經元工作的技術。"
    },
    {
      "id": "Q26",
      "num": 26,
      "type": "fill",
      "kps": [
        "KP 4.3.1"
      ],
      "answer": [
        "EarlyStopping"
      ],
      "title": "Sigmoid 函數的圖形呈 __________ 型。"
    },
    {
      "id": "Q27",
      "num": 27,
      "type": "fill",
      "kps": [
        "KP 4.3.3"
      ],
      "answer": [
        "訓練集"
      ],
      "title": "損失函數衡量的是預測值與 __________ 值之間的差距。"
    },
    {
      "id": "Q28",
      "num": 28,
      "type": "fill",
      "kps": [
        "KP 4.3.1"
      ],
      "answer": [
        "驗證集"
      ],
      "title": "當梯度的值變得極小，導致權重無法更新時，稱為梯度 __________。"
    },
    {
      "id": "Q29",
      "num": 29,
      "type": "fill",
      "kps": [
        "KP 4.3.1"
      ],
      "answer": [
        "權重衰減"
      ],
      "title": "Tanh 函數的輸出範圍是 __________。"
    },
    {
      "id": "Q30",
      "num": 30,
      "type": "fill",
      "kps": [
        "KP 4.3.5"
      ],
      "answer": [
        "泛化"
      ],
      "title": "L2 正則化又被稱為 __________ 回歸中的權重懲罰項。 ---"
    }
  ]
}